keep_cli/__init__.py
keep_cli/__main__.py
keep_cli/application.py
keep_cli/commands.py
keep_cli/constants.py
keep_cli/query.py
keep_cli/util.py
keep_cli/widget/__init__.py
keep_cli/widget/edit.py
keep_cli/widget/grid.py
keep_cli/widget/help.py
keep_cli/widget/kanban.py
keep_cli/widget/labels.py
keep_cli/widget/note.py
keep_cli/widget/search.py
keep_cli/widget/status.py
keep_cli/widget/util.py
keep_cli/widget/views.py
google_keep_cli-0.0.1.dist-info/METADATA
google_keep_cli-0.0.1.dist-info/WHEEL
google_keep_cli-0.0.1.dist-info/entry_points.txt
google_keep_cli-0.0.1.dist-info/top_level.txt
google_keep_cli-0.0.1.dist-info/RECORD
