Metadata-Version: 2.1
Name: google-keep-cli
Version: 0.0.1
Summary: Google Keep frontend for terminals
Author-email: Kai <z@kwi.li>
Project-URL: Homepage, https://github.com/kiwiz/keep-cli
Project-URL: Bug Tracker, https://github.com/kiwiz/keep-cli/issues
Classifier: Programming Language :: Python :: 3
Classifier: License :: OSI Approved :: MIT License
Classifier: Operating System :: OS Independent
Requires-Python: >=3.7
Requires-Dist: gkeepapi (>=0.14.2)
Requires-Dist: wcwidth (>=0.2.6)
Requires-Dist: urwid (>=2.0)
Requires-Dist: urwid-readline (>=0.13)
Requires-Dist: PyYAML (>=6.0)
Requires-Dist: keyring (>=23.13.1)
